reqkeeper/__init__.py
reqkeeper/core.py
reqkeeper/interceptors.py
reqkeeper/version.py
reqkeeper-1.0.0.dist-info/licenses/LICENSE
reqkeeper-1.0.0.dist-info/METADATA
reqkeeper-1.0.0.dist-info/WHEEL
reqkeeper-1.0.0.dist-info/top_level.txt
reqkeeper-1.0.0.dist-info/RECORD
