Metadata-Version: 2.4
Name: reqkeeper
Version: 1.0.0
Summary: 一个功能强大的HTTP会话持久化工具
Home-page: https://github.com/Flikify/reqkeeper
Author: Flikify
Author-email: Flikify <reqkeeper@92coco.cn>
License: MIT
Project-URL: Homepage, https://github.com/Flikify/reqkeeper
Project-URL: Bug Tracker, https://github.com/Flikify/reqkeeper/issues
Project-URL: Documentation, https://github.com/Flikify/reqkeeper#readme
Project-URL: Source Code, https://github.com/Flikify/reqkeeper
Keywords: http,requests,session,persistent,cookies,retry,interceptor
Classifier: Development Status :: 4 - Beta
Classifier: Intended Audience :: Developers
Classifier: License :: OSI Approved :: MIT License
Classifier: Operating System :: OS Independent
Classifier: Programming Language :: Python :: 3
Classifier: Programming Language :: Python :: 3.7
Classifier: Programming Language :: Python :: 3.8
Classifier: Programming Language :: Python :: 3.9
Classifier: Programming Language :: Python :: 3.10
Classifier: Programming Language :: Python :: 3.11
Classifier: Programming Language :: Python :: 3.12
Classifier: Topic :: Internet :: WWW/HTTP
Classifier: Topic :: Software Development :: Libraries :: Python Modules
Requires-Python: >=3.7
License-File: LICENSE
Requires-Dist: requests>=2.25.0
Requires-Dist: tenacity>=8.0.0
Requires-Dist: urllib3>=1.26.0
Provides-Extra: dev
Requires-Dist: pytest>=6.0; extra == "dev"
Requires-Dist: pytest-cov>=2.10; extra == "dev"
Requires-Dist: black>=21.0; extra == "dev"
Requires-Dist: flake8>=3.9; extra == "dev"
Requires-Dist: mypy>=0.812; extra == "dev"
Requires-Dist: pre-commit>=2.15; extra == "dev"
Provides-Extra: test
Requires-Dist: pytest>=6.0; extra == "test"
Requires-Dist: pytest-cov>=2.10; extra == "test"
Requires-Dist: responses>=0.18; extra == "test"
Requires-Dist: requests-mock>=1.9; extra == "test"
Dynamic: author
Dynamic: home-page
Dynamic: license-file
Dynamic: requires-python
